correlacao/__init__.py
correlacao/spearman_pearson.py
correlacao-0.0.1.dist-info/METADATA
correlacao-0.0.1.dist-info/WHEEL
correlacao-0.0.1.dist-info/top_level.txt
correlacao-0.0.1.dist-info/RECORD
