Metadata-Version: 2.1
Name: correlacao
Version: 0.0.1
Summary: Pacote para correlacionar Variáveis e Alvo - Análise de Dados
Home-page: https://github.com/Nicodemos/correlacao_variaveis_alvo
Author: Nicodemos Freitas
Author-email: nicodemosfreitas@gmail.com
License: UNKNOWN
Platform: UNKNOWN
Requires-Python: >=3.8
Requires-Dist: pandas
Requires-Dist: matplotlib
